{
  "backup_path": "./backup",
  "backup_js_path": "./backup/static/js",
  "backup_css_path": "./backup/static/css",
  "tmp_path": "./tmp",

  "bower_path": "./bower_components",
  "build_path": "./build",
  "build_view_path": "./build",
  "build_images_path": "./build/static/images",
  "build_fonts_path": "./build/static/fonts",
  "build_audio_path": "./build/static/audio",
  "build_js_path": "./build/static/js",
  "build_css_path": "./build/static/css",



  "src_path": "./src",
  "jade_path": "./src/page/jade",
  "view_path": "./src/page/html",
  "ejs_path": "./src/static/ejs",
  "js_path": "./src/static/js",
  "coffee_path": "./src/static/coffee",
  "audio_path": "./src/static/audio",
  "css_path": "./src/static/css",
  "stylus_path": "./src/static/stylus",
  "images_path": "./src/static/images",
  "fonts_path": "./src/static/fonts"
}
